[
    {
        "id": "6a0b4ecc-2bf2-443d-8991-f5d5abf261d9",
        "name": "Azul",
        "id_bgg": 230802,
        "price_category": "Fogo",
        "price_base": 40,
        "mechanics": [
            "Colocação de Peças",
            "Construção a partir de Modelo",
            "Bônus de Fim de Jogo",
            "Compra Aberta",
            "Ordem do Turno: Ação de Reivindicação"
        ],
        "min_players": 2,
        "max_players": 4,
        "playtime": 45,
        "complexity": 0,
        "theme": "Arte",
        "min_age": 8,
        "slug": "azul",
        "link_ludopedia": "https://ludopedia.com.br/jogo/azul",
        "categories": [
            "Estratégia Abstrata",
            "Quebra-Cabeça"
        ]
    },
    {
        "id": "9c66c56f-6956-4c39-93ae-4a57a0ddf02f",
        "name": "Caiu Perdeu",
        "id_bgg": 23953,
        "price_category": "Brisa",
        "price_base": 10,
        "mechanics": [
            "Construção a partir de Modelo",
            "Colocação de Peças",
            "Eliminação de Jogadores",
            "Empilhar e Equilibrar",
            "Perdedor Único",
            "Remoção Física"
        ],
        "min_players": 1,
        "max_players": 8,
        "playtime": 20,
        "complexity": 0,
        "theme": "Educacional",
        "min_age": 6,
        "slug": "caiu-perdeu",
        "link_ludopedia": "https://ludopedia.com.br/jogo/caiu-perdeu",
        "categories": [
            "Jogo Festivo"
        ]
    },
    {
        "id": "99c43850-12d7-4b82-936e-1f5bf1563222",
        "name": "Dobble",
        "id_bgg": 63268,
        "price_category": "Faísca",
        "price_base": 20,
        "mechanics": [
            "Reconhecimento de Padrões",
            "Tempo Real",
            "Batata Quente",
            "Correspondência Rápida"
        ],
        "min_players": 2,
        "max_players": 8,
        "playtime": 10,
        "complexity": 0,
        "theme": "Educacional",
        "min_age": 7,
        "slug": "dobble-spot-it",
        "link_ludopedia": "https://ludopedia.com.br/jogo/dobble-spot-it",
        "categories": [
            "Jogo de Cartas",
            "Jogo Festivo"
        ]
    },
    {
        "id": "69d405f0-3576-48c8-b4b0-c3f86f61e17e",
        "name": "Bananagrams",
        "id_bgg": 27225,
        "price_category": "Faísca",
        "price_base": 20,
        "mechanics": [
            "Colocação de Peças",
            "Tempo Real",
            "Corrida",
            "Ortografia",
            "Solo / Solitário"
        ],
        "min_players": 1,
        "max_players": 8,
        "playtime": 15,
        "complexity": 0,
        "theme": "Educacional",
        "min_age": 7,
        "slug": "bananagrams",
        "link_ludopedia": "https://ludopedia.com.br/jogo/bananagrams",
        "categories": [
            "Jogo de Entrada",
            "Jogo Festivo"
        ]
    },
    {
        "id": "e2c78dcf-4821-436b-a46f-3519c3aa84f6",
        "name": "Jaipur",
        "id_bgg": 54043,
        "price_category": "Chama",
        "price_base": 30,
        "mechanics": [
            "Gerenciamento de Mãos",
            "Colecionar Conjuntos",
            "Especulação de Commodities",
            "Compra Aberta",
            "Pontuar e Reiniciar",
            "Bônus de Fim de Jogo",
            "Corrida",
            "Fim por Morte Súbita",
            "Mercado",
            "Ordem do Turno: Progressivo",
            "Pontos de Vitória Ocultos",
            "Preparação Variável"
        ],
        "min_players": 2,
        "max_players": 2,
        "playtime": 30,
        "complexity": 0,
        "theme": "Animais",
        "min_age": 12,
        "slug": "jaipur",
        "link_ludopedia": "https://ludopedia.com.br/jogo/jaipur",
        "categories": [
            "Jogo de Cartas"
        ]
    },
    {
        "id": "a80de0a2-3803-4b85-ad99-edbe20dbea20",
        "name": "Kariba",
        "id_bgg": 84732,
        "price_category": "Faísca",
        "price_base": 20,
        "mechanics": [
            "Gerenciamento de Mãos",
            "Colecionar Conjuntos",
            "Colocação de Peças",
            "Pedra, Papel e Tesoura",
            "Toma Essa"
        ],
        "min_players": 2,
        "max_players": 4,
        "playtime": 15,
        "complexity": 0,
        "theme": "Animais",
        "min_age": 8,
        "slug": "kariba",
        "link_ludopedia": "https://ludopedia.com.br/jogo/kariba",
        "categories": [
            "Jogo de Cartas",
            "Jogo de Entrada",
            "Carteado"
        ]
    },
    {
        "id": "6421415b-fd80-4430-bb7e-24d67b5851b3",
        "name": "LHAMA",
        "id_bgg": 266083,
        "price_category": "Chama",
        "price_base": 30,
        "mechanics": [
            "Gerenciamento de Mãos",
            "Force sua sorte",
            "Escalada"
        ],
        "min_players": 2,
        "max_players": 6,
        "playtime": 20,
        "complexity": 0,
        "theme": "Animais",
        "min_age": 8,
        "slug": "lhama",
        "link_ludopedia": "https://ludopedia.com.br/jogo/lhama",
        "categories": [
            "Jogo de Cartas",
            "Jogo de Entrada",
            "Carteado"
        ]
    },
    {
        "id": "3078f991-b970-41e1-845e-1db262fc88cf",
        "name": "Marrakech",
        "id_bgg": 29223,
        "price_category": "Fogo",
        "price_base": 40,
        "mechanics": [
            "Colocação de Peças",
            "Influência / Maioria na Área",
            "Rolar / Girar e Mover"
        ],
        "min_players": 2,
        "max_players": 4,
        "playtime": 30,
        "complexity": 0,
        "theme": "Cultura Oriental",
        "min_age": 6,
        "slug": "marrakech-suleika",
        "link_ludopedia": "https://ludopedia.com.br/jogo/marrakech-suleika",
        "categories": []
    },
    {
        "id": "565c7dd9-e3e8-48ea-83b3-43b995840551",
        "name": "Quem Foi?",
        "id_bgg": 241491,
        "price_category": "Faísca",
        "price_base": 20,
        "mechanics": [
            "Memória",
            "Gerenciamento de Mãos",
            "Perdedor Único"
        ],
        "min_players": 3,
        "max_players": 6,
        "playtime": 15,
        "complexity": 0,
        "theme": "Animais",
        "min_age": 6,
        "slug": "who-did-it",
        "link_ludopedia": "https://ludopedia.com.br/jogo/who-did-it",
        "categories": [
            "Jogo de Cartas"
        ]
    },
    {
        "id": "6cf22d01-a762-460d-bd84-e5207fb650f0",
        "name": "Trio",
        "id_bgg": 352515,
        "price_category": "Faísca",
        "price_base": 20,
        "mechanics": [
            "Colecionar Conjuntos",
            "Memória",
            "Dedução"
        ],
        "min_players": 2,
        "max_players": 6,
        "playtime": 15,
        "complexity": 0,
        "theme": "",
        "min_age": 8,
        "slug": "trio",
        "link_ludopedia": "https://ludopedia.com.br/jogo/trio",
        "categories": [
            "Jogo de Cartas",
            "Jogo de Entrada",
            "Jogo Festivo"
        ]
    },
    {
        "id": "53b8de8a-e01b-49ba-95f4-8dcf169c5b99",
        "name": "Uno",
        "id_bgg": 2223,
        "price_category": "Brisa",
        "price_base": 10,
        "mechanics": [
            "Gerenciamento de Mãos",
            "Combinação",
            "Pontuar e Reiniciar",
            "Toma Essa",
            "Corrida",
            "Perder a Vez",
            "Ordem de Turno: Interrupções"
        ],
        "min_players": 2,
        "max_players": 10,
        "playtime": 30,
        "complexity": 0,
        "theme": "",
        "min_age": 7,
        "slug": "uno",
        "link_ludopedia": "https://ludopedia.com.br/jogo/uno",
        "categories": [
            "Jogo de Cartas",
            "Jogo Festivo",
            "Carteado"
        ]
    },
    {
        "id": "811a5396-cc4f-4d97-b8a0-c05efc39b10b",
        "name": "Uno Flip!",
        "id_bgg": 271460,
        "price_category": "Faísca",
        "price_base": 20,
        "mechanics": [
            "Gerenciamento de Mãos",
            "Toma Essa"
        ],
        "min_players": 2,
        "max_players": 10,
        "playtime": 40,
        "complexity": 0,
        "theme": "",
        "min_age": 7,
        "slug": "uno-flip",
        "link_ludopedia": "https://ludopedia.com.br/jogo/uno-flip",
        "categories": [
            "Jogo de Cartas",
            "Carteado"
        ]
    },
    {
        "id": "217495ce-c036-4ab3-a98f-994e8ed3847f",
        "name": "War: O Jogo da Estratégia",
        "id_bgg": 33112,
        "price_category": "Chama",
        "price_base": 30,
        "mechanics": [
            "Influência / Maioria na Área",
            "Movimento de Área",
            "Rolagem de Dados",
            "Colecionar Conjuntos",
            "Eliminação de Jogadores"
        ],
        "min_players": 3,
        "max_players": 6,
        "playtime": 120,
        "complexity": 0,
        "theme": "Guerra",
        "min_age": 10,
        "slug": "war",
        "link_ludopedia": "https://ludopedia.com.br/jogo/war",
        "categories": [
            "Jogo de Dados",
            "Jogo de Guerra"
        ]
    },
    {
        "id": "45a3804d-9f15-4a70-90f5-d3fb56316a06",
        "name": "Telma (2ª Edição)",
        "id_bgg": 623822,
        "price_category": "Faísca",
        "price_base": 20,
        "mechanics": [
            "Memória",
            "Reconhecimento de Padrões"
        ],
        "min_players": 4,
        "max_players": 8,
        "playtime": 20,
        "complexity": 0,
        "theme": "Humor",
        "min_age": 6,
        "slug": "telma-2-edicao",
        "link_ludopedia": "https://ludopedia.com.br/jogo/telma-2-edicao",
        "categories": [
            "Jogo de Cartas",
            "Jogo Festivo"
        ]
    },
    {
        "id": "9d33664c-1b3c-42a8-a6f4-6132f23f8c32",
        "name": "Harmonies",
        "id_bgg": 414317,
        "price_category": "Fogo",
        "price_base": 40,
        "mechanics": [
            "Construção a partir de Modelo",
            "Colocação de Peças",
            "Combinação",
            "Bônus de Fim de Jogo",
            "Ordem do Turno: Progressivo",
            "Compra Aberta"
        ],
        "min_players": 1,
        "max_players": 4,
        "playtime": 45,
        "complexity": 0,
        "theme": "Animais",
        "min_age": 10,
        "slug": "harmonies",
        "link_ludopedia": "https://ludopedia.com.br/jogo/harmonies",
        "categories": [
            "Estratégia Abstrata"
        ]
    },
    {
        "id": "7c4153e8-f592-4576-866a-1304e147d580",
        "name": "Bloqueio",
        "id_bgg": 624,
        "price_category": "Faísca",
        "price_base": 20,
        "mechanics": [
            "Movimento em Grades",
            "Conexões",
            "Corrida",
            "Grade com Quadrados"
        ],
        "min_players": 2,
        "max_players": 4,
        "playtime": 20,
        "complexity": 0,
        "theme": "",
        "min_age": 6,
        "slug": "bloqueio",
        "link_ludopedia": "https://ludopedia.com.br/jogo/quoridor",
        "categories": [
            "Estratégia Abstrata"
        ]
    },
    {
        "id": "6996ed55-45a4-4529-91d1-a7e1feb05424",
        "name": "boop.",
        "id_bgg": 355433,
        "price_category": "Chama",
        "price_base": 30,
        "mechanics": [
            "Construção a partir de Modelo",
            "Movimento em Grades",
            "Deslizar / Empurrar",
            "Grade com Quadrados",
            "Ordem do Turno: Progressivo"
        ],
        "min_players": 2,
        "max_players": 2,
        "playtime": 30,
        "complexity": 0,
        "theme": "Animais",
        "min_age": 10,
        "slug": "boop",
        "link_ludopedia": "https://ludopedia.com.br/jogo/boop",
        "categories": [
            "Estratégia Abstrata"
        ]
    },
    {
        "id": "4cfaa728-87f0-40d6-bc03-abf692a0a672",
        "name": "Café",
        "id_bgg": 284936,
        "price_category": "Chama",
        "price_base": 30,
        "mechanics": [
            "Pegar e Entregar",
            "Pontos de Ação",
            "Colocação de Peças",
            "Camadas de Componentes",
            "Fundir e Espalhar",
            "Maior Pontuação Baixa",
            "Solo / Solitário"
        ],
        "min_players": 1,
        "max_players": 4,
        "playtime": 45,
        "complexity": 0,
        "theme": "Economia / Produção",
        "min_age": 14,
        "slug": "cafe",
        "link_ludopedia": "https://ludopedia.com.br/jogo/cafe",
        "categories": [
            "Jogo de Cartas"
        ]
    },
    {
        "id": "762e7ba0-5385-43a9-bbee-92423e09e25b",
        "name": "Color Addict",
        "id_bgg": 124954,
        "price_category": "Brisa",
        "price_base": 10,
        "mechanics": [
            "Tempo Real",
            "Batata Quente",
            "Correspondência Rápida",
            "Reconhecimento de Padrões"
        ],
        "min_players": 2,
        "max_players": 6,
        "playtime": 15,
        "complexity": 0,
        "theme": "Arte",
        "min_age": 7,
        "slug": "color-addict",
        "link_ludopedia": "https://ludopedia.com.br/jogo/color-addict",
        "categories": [
            "Jogo de Cartas",
            "Jogo de Entrada",
            "Jogo Festivo",
            "Carteado"
        ]
    },
    {
        "id": "f12ccd90-b6e3-49eb-ad92-2c3f0dddaa25",
        "name": "ColorFox",
        "id_bgg": 193831,
        "price_category": "Chama",
        "price_base": 30,
        "mechanics": [
            "Colecionar Conjuntos",
            "Colocação de Peças",
            "Gerenciamento de Mãos"
        ],
        "min_players": 2,
        "max_players": 4,
        "playtime": 15,
        "complexity": 0,
        "theme": "",
        "min_age": 6,
        "slug": "colorfox",
        "link_ludopedia": "https://ludopedia.com.br/jogo/colorfox",
        "categories": [
            "Estratégia Abstrata",
            "Jogo de Cartas",
            "Jogo de Entrada",
            "Jogo Festivo"
        ]
    },
    {
        "id": "39a8276c-101d-4752-8e4d-64c2439f2488",
        "name": "Fungi",
        "id_bgg": 122298,
        "price_category": "Chama",
        "price_base": 30,
        "mechanics": [
            "Gerenciamento de Mãos",
            "Colecionar Conjuntos",
            "Combinação",
            "Compra Aberta",
            "Deslizar / Empurrar",
            "Ordem do Turno: Progressivo"
        ],
        "min_players": 0,
        "max_players": 0,
        "playtime": 40,
        "complexity": 0,
        "theme": "Aventura",
        "min_age": 0,
        "slug": "fungi-morels",
        "link_ludopedia": "https://ludopedia.com.br/jogo/fungi-morels",
        "categories": [
            "Jogo de Cartas"
        ]
    },
    {
        "id": "f51a335c-9ecf-408a-84d3-e0407ecd89c3",
        "name": "LHAMA Dados",
        "id_bgg": 325853,
        "price_category": "Chama",
        "price_base": 30,
        "mechanics": [
            "Rolagem de Dados",
            "Force sua sorte"
        ],
        "min_players": 2,
        "max_players": 6,
        "playtime": 20,
        "complexity": 0,
        "theme": "Animais",
        "min_age": 0,
        "slug": "lama-dice",
        "link_ludopedia": "https://ludopedia.com.br/jogo/lama-dice",
        "categories": [
            "Jogo de Cartas",
            "Jogo de Dados",
            "Jogo Festivo"
        ]
    },
    {
        "id": "9d33664e-5453-4932-9446-82f360e1d777",
        "name": "Córdoba",
        "id_bgg": 424515,
        "price_category": "Brisa",
        "price_base": 10,
        "mechanics": [
            "Fundir e Espalhar",
            "Resolução de Conflitos por Cartas"
        ],
        "min_players": 0,
        "max_players": 0,
        "playtime": 10,
        "complexity": 0,
        "theme": "História",
        "min_age": 0,
        "slug": "cordoba",
        "link_ludopedia": "https://ludopedia.com.br/jogo/cordoba",
        "categories": [
            "Jogo de Cartas",
            "Jogo de Entrada"
        ]
    },
    {
        "id": "8e2d7e09-9ce8-4662-bc14-c43c9c5e05a2",
        "name": "Duo Regna",
        "id_bgg": 392117,
        "price_category": "Brisa",
        "price_base": 10,
        "mechanics": [
            "Seleção de Ação Simultânea",
            "Cabo-de-Guerra",
            "Pedra, Papel e Tesoura",
            "Gerenciamento de Mãos",
            "Memória"
        ],
        "min_players": 0,
        "max_players": 0,
        "playtime": 10,
        "complexity": 0,
        "theme": "Medieval",
        "min_age": 0,
        "slug": "duo-regna",
        "link_ludopedia": "https://ludopedia.com.br/jogo/duo-regna",
        "categories": [
            "Jogo de Cartas"
        ]
    },
    {
        "id": "f0d987c9-ab71-4cc5-a0a6-9739275267c5",
        "name": "Glifos",
        "id_bgg": 412418,
        "price_category": "Brisa",
        "price_base": 10,
        "mechanics": [
            "Memória",
            "Reconhecimento de Padrões",
            "Solo / Solitário"
        ],
        "min_players": 1,
        "max_players": 5,
        "playtime": 10,
        "complexity": 0,
        "theme": "Civilização",
        "min_age": 0,
        "slug": "glifos",
        "link_ludopedia": "https://ludopedia.com.br/jogo/glifos",
        "categories": [
            "Jogo de Cartas",
            "Jogo de Entrada"
        ]
    },
    {
        "id": "fdf4cd14-49c9-4895-92ff-afeb8a97fc6c",
        "name": "Evergreen",
        "id_bgg": 363307,
        "price_category": "Fogo",
        "price_base": 40,
        "mechanics": [
            "Influência / Maioria na Área",
            "Bônus de Fim de Jogo",
            "Compra Aberta"
        ],
        "min_players": 1,
        "max_players": 4,
        "playtime": 45,
        "complexity": 0,
        "theme": "Meio Ambiente",
        "min_age": 0,
        "slug": "evergreen",
        "link_ludopedia": "https://ludopedia.com.br/jogo/evergreen",
        "categories": [
            "Estratégia Abstrata"
        ]
    },
    {
        "id": "3354bb0d-7177-4920-b29a-faa637a3cb0a",
        "name": "Hanabi",
        "id_bgg": 98778,
        "price_category": "Faísca",
        "price_base": 20,
        "mechanics": [
            "Gerenciamento de Mãos",
            "Cooperativo",
            "Memória",
            "Dedução",
            "Colecionar Conjuntos"
        ],
        "min_players": 2,
        "max_players": 5,
        "playtime": 30,
        "complexity": 0,
        "theme": "Cultura Oriental",
        "min_age": 0,
        "slug": "hanabi",
        "link_ludopedia": "https://ludopedia.com.br/jogo/hanabi",
        "categories": [
            "Jogo de Cartas",
            "Jogo de Entrada",
            "Jogo Festivo"
        ]
    },
    {
        "id": "bfb6524b-7b52-4d8e-9ff2-89675db64691",
        "name": "Hippo",
        "id_bgg": 234105,
        "price_category": "Faísca",
        "price_base": 20,
        "mechanics": [
            "Rolagem de Dados",
            "Tabuleiro Modular",
            "Influência / Maioria na Área"
        ],
        "min_players": 2,
        "max_players": 4,
        "playtime": 15,
        "complexity": 0,
        "theme": "Animais",
        "min_age": 0,
        "slug": "hippo",
        "link_ludopedia": "https://ludopedia.com.br/jogo/hippo",
        "categories": [
            "Jogo de Cartas",
            "Jogo de Dados",
            "Jogo de Entrada"
        ]
    },
    {
        "id": "9d7854e0-e880-4854-884f-997ad68c0da7",
        "name": "Homem Batata",
        "id_bgg": 137155,
        "price_category": "Faísca",
        "price_base": 20,
        "mechanics": [
            "Vazas / Truques"
        ],
        "min_players": 2,
        "max_players": 5,
        "playtime": 40,
        "complexity": 0,
        "theme": "Humor",
        "min_age": 0,
        "slug": "potato-man",
        "link_ludopedia": "https://ludopedia.com.br/jogo/potato-man",
        "categories": [
            "Jogo de Cartas",
            "Carteado"
        ]
    },
    {
        "id": "7056cc8e-e4f3-47bb-a325-b1f85d3a546d",
        "name": "Istanbul",
        "id_bgg": 148949,
        "price_category": "Vulcão",
        "price_base": 50,
        "mechanics": [
            "Movimento em Grades",
            "Pegar e Entregar",
            "Rolagem de Dados",
            "Tabuleiro Modular",
            "Alocação de Trabalhadores",
            "Construção de Redes e Rotas",
            "Contratos",
            "Corrida",
            "Preparação Variável"
        ],
        "min_players": 2,
        "max_players": 5,
        "playtime": 60,
        "complexity": 0,
        "theme": "Cultura Oriental",
        "min_age": 0,
        "slug": "istanbul",
        "link_ludopedia": "https://ludopedia.com.br/jogo/istanbul",
        "categories": []
    },
    {
        "id": "9937596f-77b7-4bb1-9d9a-ec04d9dee92c",
        "name": "KLASK",
        "id_bgg": 165722,
        "price_category": "Vulcão",
        "price_base": 50,
        "mechanics": [
            "Pontuar e Reiniciar",
            "Tempo Real"
        ],
        "min_players": 0,
        "max_players": 0,
        "playtime": 10,
        "complexity": 0,
        "theme": "",
        "min_age": 0,
        "slug": "klask",
        "link_ludopedia": "https://ludopedia.com.br/jogo/klask",
        "categories": [
            "Destreza",
            "Jogo Festivo"
        ]
    },
    {
        "id": "d26f6bd8-b378-4427-9678-e57565ccc65a",
        "name": "Lata",
        "id_bgg": 374201,
        "price_category": "Chama",
        "price_base": 30,
        "mechanics": [
            "Contratos",
            "Influência / Maioria na Área",
            "Ordem do Turno: Leilão",
            "Pontos de Ação"
        ],
        "min_players": 1,
        "max_players": 4,
        "playtime": 45,
        "complexity": 0,
        "theme": "Economia / Produção",
        "min_age": 0,
        "slug": "lata",
        "link_ludopedia": "https://ludopedia.com.br/jogo/lata",
        "categories": [
            "Jogo de Cartas"
        ]
    },
    {
        "id": "9d33664d-f3b0-49ed-b20d-895f0be7a103",
        "name": "Lemur",
        "id_bgg": 422993,
        "price_category": "Brisa",
        "price_base": 10,
        "mechanics": [
            "Gerenciamento de Mãos",
            "Combinação"
        ],
        "min_players": 2,
        "max_players": 5,
        "playtime": 10,
        "complexity": 0,
        "theme": "Animais",
        "min_age": 0,
        "slug": "lemur",
        "link_ludopedia": "https://ludopedia.com.br/jogo/lemur",
        "categories": [
            "Jogo de Cartas"
        ]
    },
    {
        "id": "4620694c-157a-4a77-8eec-10678e18d01c",
        "name": "O Que O Quê",
        "id_bgg": 392110,
        "price_category": "Brisa",
        "price_base": 10,
        "mechanics": [
            "Correspondência Rápida",
            "Reconhecimento de Padrões",
            "Tempo Real"
        ],
        "min_players": 2,
        "max_players": 5,
        "playtime": 10,
        "complexity": 0,
        "theme": "",
        "min_age": 0,
        "slug": "o-que-o-que",
        "link_ludopedia": "https://ludopedia.com.br/jogo/o-que-o-que",
        "categories": [
            "Jogo de Cartas",
            "Jogo Festivo"
        ]
    },
    {
        "id": "72cddb50-1250-4474-8b62-a06b7a7703ab",
        "name": "Palm Island",
        "id_bgg": 239464,
        "price_category": "Faísca",
        "price_base": 20,
        "mechanics": [
            "Seleção de Ação Simultânea",
            "Gerenciamento de Mãos",
            "Memória",
            "Cooperativo",
            "Construção de Baralho, Bolsas e Peças"
        ],
        "min_players": 1,
        "max_players": 2,
        "playtime": 15,
        "complexity": 0,
        "theme": "Meio Ambiente",
        "min_age": 0,
        "slug": "palm-island",
        "link_ludopedia": "https://ludopedia.com.br/jogo/palm-island",
        "categories": [
            "Jogo de Cartas",
            "Jogo de Entrada"
        ]
    },
    {
        "id": "640e4bd0-cdce-4d3f-810b-d01c0f5d9774",
        "name": "Potion Explosion",
        "id_bgg": 180974,
        "price_category": "Fogo",
        "price_base": 40,
        "mechanics": [
            "Colecionar Conjuntos",
            "Reconhecimento de Padrões"
        ],
        "min_players": 2,
        "max_players": 4,
        "playtime": 45,
        "complexity": 0,
        "theme": "Fantasia",
        "min_age": 0,
        "slug": "potion-explosion",
        "link_ludopedia": "https://ludopedia.com.br/jogo/potion-explosion",
        "categories": []
    },
    {
        "id": "03876004-21dd-4ca3-98e9-0196e5ca75d9",
        "name": "Qui-Quitanda",
        "id_bgg": 392118,
        "price_category": "Brisa",
        "price_base": 10,
        "mechanics": [
            "Cooperativo",
            "Reconhecimento de Padrões",
            "Solo / Solitário"
        ],
        "min_players": 1,
        "max_players": 4,
        "playtime": 10,
        "complexity": 0,
        "theme": "Gastronomia",
        "min_age": 0,
        "slug": "qui-quitanda",
        "link_ludopedia": "https://ludopedia.com.br/jogo/qui-quitanda",
        "categories": [
            "Estratégia Abstrata",
            "Jogo de Cartas",
            "Jogo de Entrada"
        ]
    },
    {
        "id": "3570b9ce-1666-48d8-827e-b36dcb8ae4ac",
        "name": "Splendor Duel",
        "id_bgg": 364073,
        "price_category": "Chama",
        "price_base": 30,
        "mechanics": [
            "Colecionar Conjuntos",
            "Compra Aberta",
            "Contratos",
            "Corrida"
        ],
        "min_players": 0,
        "max_players": 0,
        "playtime": 30,
        "complexity": 0,
        "theme": "Economia / Produção",
        "min_age": 0,
        "slug": "splendor-duel",
        "link_ludopedia": "https://ludopedia.com.br/jogo/splendor-duel",
        "categories": [
            "Jogo de Cartas"
        ]
    },
    {
        "id": "1d83e627-4095-4bd5-b925-f097384cd5e9",
        "name": "Splito",
        "id_bgg": 359878,
        "price_category": "Chama",
        "price_base": 30,
        "mechanics": [
            "Seleção de Ação Simultânea",
            "Gerenciamento de Mãos",
            "Compartilhamento entre Vizinhos"
        ],
        "min_players": 2,
        "max_players": 8,
        "playtime": 20,
        "complexity": 0,
        "theme": "",
        "min_age": 0,
        "slug": "splito",
        "link_ludopedia": "https://ludopedia.com.br/jogo/splito",
        "categories": [
            "Estratégia Abstrata",
            "Jogo de Cartas",
            "Jogo de Entrada"
        ]
    },
    {
        "id": "b57426d9-7174-4893-9ea9-673ca11c6b9d",
        "name": "That's Not a Hat",
        "id_bgg": 375651,
        "price_category": "Faísca",
        "price_base": 20,
        "mechanics": [
            "Dedução",
            "Apostas e Blefes",
            "Memória"
        ],
        "min_players": 3,
        "max_players": 8,
        "playtime": 15,
        "complexity": 0,
        "theme": "Genérico/Universal",
        "min_age": 0,
        "slug": "that-s-not-a-hat",
        "link_ludopedia": "https://ludopedia.com.br/jogo/that-s-not-a-hat",
        "categories": [
            "Estratégia Abstrata",
            "Jogo de Cartas",
            "Jogo Festivo"
        ]
    },
    {
        "id": "01065147-8504-49b1-9651-b68e5ef6b6a5",
        "name": "The Game",
        "id_bgg": 173090,
        "price_category": "Faísca",
        "price_base": 20,
        "mechanics": [
            "Gerenciamento de Mãos",
            "Cooperativo",
            "Comunicação Limitada",
            "Solo / Solitário"
        ],
        "min_players": 1,
        "max_players": 5,
        "playtime": 20,
        "complexity": 0,
        "theme": "",
        "min_age": 0,
        "slug": "the-game",
        "link_ludopedia": "https://ludopedia.com.br/jogo/the-game",
        "categories": [
            "Jogo de Cartas"
        ]
    },
    {
        "id": "b1be2217-bdbf-4ac7-b6a4-32f9b60487f5",
        "name": "UeStop!",
        "id_bgg": 355914,
        "price_category": "Faísca",
        "price_base": 20,
        "mechanics": [
            "Combinação"
        ],
        "min_players": 2,
        "max_players": 6,
        "playtime": 20,
        "complexity": 0,
        "theme": "",
        "min_age": 0,
        "slug": "uestop",
        "link_ludopedia": "https://ludopedia.com.br/jogo/uestop",
        "categories": [
            "Jogo de Cartas",
            "Jogo de Entrada",
            "Jogo Festivo"
        ]
    },
    {
        "id": "5beb239a-3f17-4881-9233-ce731d172643",
        "name": "Alieninjas",
        "id_bgg": 357883,
        "price_category": "Chama",
        "price_base": 30,
        "mechanics": [
            "Seleção de Ação Simultânea",
            "Construção a partir de Modelo",
            "Force sua sorte",
            "Gerenciamento de Mãos",
            "Memória",
            "Tempo Real",
            "Reconhecimento de Padrões"
        ],
        "min_players": 2,
        "max_players": 6,
        "playtime": 30,
        "complexity": 0,
        "theme": "Fantasia",
        "min_age": 0,
        "slug": "alieninjas",
        "link_ludopedia": "https://ludopedia.com.br/jogo/alieninjas",
        "categories": [
            "Jogo de Cartas",
            "Jogo Festivo"
        ]
    },
    {
        "id": "174b14b4-ee26-47f0-aedb-2e31cf6f33c7",
        "name": "Color Addict Kids",
        "id_bgg": 23953,
        "price_category": "Brisa",
        "price_base": 10,
        "mechanics": [
            "Gerenciamento de Mãos"
        ],
        "min_players": 2,
        "max_players": 4,
        "playtime": 15,
        "complexity": 0,
        "theme": "Educacional",
        "min_age": 0,
        "slug": "color-addict-kidz",
        "link_ludopedia": "https://ludopedia.com.br/jogo/color-addict-kidz",
        "categories": [
            "Jogo de Cartas"
        ]
    },
    {
        "id": "e69b5c60-9b9f-4f43-8df1-ddda846aec03",
        "name": "Diversity",
        "id_bgg": 23953,
        "price_category": "Brisa",
        "price_base": 10,
        "mechanics": [
            "Colecionar Conjuntos",
            "Compra Aberta",
            "Conexões",
            "Contratos"
        ],
        "min_players": 2,
        "max_players": 4,
        "playtime": 20,
        "complexity": 0,
        "theme": "",
        "min_age": 0,
        "slug": "diversity",
        "link_ludopedia": "https://ludopedia.com.br/jogo/diversity",
        "categories": [
            "Jogo de Cartas",
            "Jogo de Entrada"
        ]
    },
    {
        "id": "42a047f1-8079-486b-aaea-a3177d6e44a3",
        "name": "Glitches",
        "id_bgg": 413860,
        "price_category": "Brisa",
        "price_base": 10,
        "mechanics": [
            "Reconhecimento de Padrões"
        ],
        "min_players": 0,
        "max_players": 0,
        "playtime": 10,
        "complexity": 0,
        "theme": "Ficção Científica",
        "min_age": 0,
        "slug": "glitches",
        "link_ludopedia": "https://ludopedia.com.br/jogo/glitches",
        "categories": [
            "Jogo de Cartas",
            "Jogo de Entrada"
        ]
    },
    {
        "id": "9e5e9fda-54cc-4e64-9ccd-0d801039c323",
        "name": "Impromptu - O Jogo do Improviso",
        "id_bgg": 23953,
        "price_category": "Chama",
        "price_base": 30,
        "mechanics": [
            "Dedução",
            "Memória",
            "Narração de Histórias",
            "Pistas Direcionadas"
        ],
        "min_players": 2,
        "max_players": 6,
        "playtime": 45,
        "complexity": 0,
        "theme": "Humor",
        "min_age": 0,
        "slug": "impromptu-o-jogo-do-improviso",
        "link_ludopedia": "https://ludopedia.com.br/jogo/impromptu-o-jogo-do-improviso",
        "categories": [
            "Jogo Festivo"
        ]
    },
    {
        "id": "9d33664d-bd72-430b-aba1-fb827e97af2f",
        "name": "Isso Não É Um Jogo",
        "id_bgg": 23953,
        "price_category": "Chama",
        "price_base": 30,
        "mechanics": [
            "Cartas Multiuso",
            "Conexões",
            "Cooperativo",
            "Narração de Histórias",
            "Perguntas e Respostas"
        ],
        "min_players": 1,
        "max_players": 10,
        "playtime": 30,
        "complexity": 0,
        "theme": "Genérico/Universal",
        "min_age": 0,
        "slug": "isso-nao-e-um-jogo",
        "link_ludopedia": "https://ludopedia.com.br/jogo/isso-nao-e-um-jogo",
        "categories": [
            "Jogo de Cartas"
        ]
    },
    {
        "id": "26d764b9-c09a-4e6e-b443-21b97819a697",
        "name": "Kingdomino",
        "id_bgg": 204583,
        "price_category": "Chama",
        "price_base": 30,
        "mechanics": [
            "Colocação de Peças",
            "Compra Aberta",
            "Ordem de Turno: Baseado em Estatísticas"
        ],
        "min_players": 2,
        "max_players": 4,
        "playtime": 15,
        "complexity": 0,
        "theme": "Medieval",
        "min_age": 0,
        "slug": "kingdomino",
        "link_ludopedia": "https://ludopedia.com.br/jogo/kingdomino",
        "categories": [
            "Estratégia Abstrata",
            "Jogo de Entrada",
            "Quebra-Cabeça"
        ]
    },
    {
        "id": "f3673fb8-c62b-4655-99b2-2dbf19980666",
        "name": "Next Station: London",
        "id_bgg": 353545,
        "price_category": "Chama",
        "price_base": 30,
        "mechanics": [
            "Construção de Redes e Rotas",
            "Contratos",
            "Desenho de Linhas",
            "Papel e Caneta",
            "Solo / Solitário",
            "Jogadores com Diferentes Habilidades",
            "Conexões"
        ],
        "min_players": 1,
        "max_players": 4,
        "playtime": 25,
        "complexity": 0,
        "theme": "Transportes",
        "min_age": 0,
        "slug": "next-station-london",
        "link_ludopedia": "https://ludopedia.com.br/jogo/next-station-london",
        "categories": [
            "Estratégia Abstrata",
            "Jogo de Entrada"
        ]
    },
    {
        "id": "a7f72360-6090-4bce-bd85-4030e0049ca5",
        "name": "Takenokolor",
        "id_bgg": 373636,
        "price_category": "Chama",
        "price_base": 30,
        "mechanics": [
            "Bônus de Fim de Jogo",
            "Compra Aberta",
            "Desenhar",
            "Múltiplos Mapas",
            "Papel e Caneta",
            "Rolagem de Dados"
        ],
        "min_players": 2,
        "max_players": 4,
        "playtime": 30,
        "complexity": 0,
        "theme": "Animais",
        "min_age": 0,
        "slug": "takenokolor",
        "link_ludopedia": "https://ludopedia.com.br/jogo/takenokolor",
        "categories": []
    },
    {
        "id": "d8582a16-d9cd-4f9d-919c-479e37bc9408",
        "name": "Tapa Certo",
        "id_bgg": 23953,
        "price_category": "Brisa",
        "price_base": 10,
        "mechanics": [
            "Seleção de Ação Simultânea"
        ],
        "min_players": 2,
        "max_players": 3,
        "playtime": 30,
        "complexity": 0,
        "theme": "Animais",
        "min_age": 0,
        "slug": "tapa-certo",
        "link_ludopedia": "https://ludopedia.com.br/jogo/tapa-certo",
        "categories": [
            "Jogo Festivo"
        ]
    },
    {
        "id": "34bd8ca3-8ccf-4673-a8ae-94b6f7250743",
        "name": "Turing Machine",
        "id_bgg": 356123,
        "price_category": "Vulcão",
        "price_base": 50,
        "mechanics": [
            "Dedução"
        ],
        "min_players": 1,
        "max_players": 4,
        "playtime": 20,
        "complexity": 0,
        "theme": "História",
        "min_age": 0,
        "slug": "turing-machine",
        "link_ludopedia": "https://ludopedia.com.br/jogo/turing-machine",
        "categories": [
            "Quebra-Cabeça"
        ]
    },
    {
        "id": "122da602-a7b1-486a-9bf8-e7d5e08b1da2",
        "name": "Verdant",
        "id_bgg": 334065,
        "price_category": "Fogo",
        "price_base": 40,
        "mechanics": [
            "Colecionar Conjuntos",
            "Colocação de Peças",
            "Construção a partir de Modelo",
            "Preparação Variável",
            "Solo / Solitário",
            "Cobertura de Grade",
            "Compra Aberta",
            "Valorização dos Recursos Não Escolhidos",
            "Contratos"
        ],
        "min_players": 1,
        "max_players": 5,
        "playtime": 60,
        "complexity": 0,
        "theme": "Educacional",
        "min_age": 0,
        "slug": "verdant",
        "link_ludopedia": "https://ludopedia.com.br/jogo/verdant",
        "categories": [
            "Jogo de Cartas",
            "Quebra-Cabeça"
        ]
    },
    {
        "id": "f82250ea-8050-45ee-8ad5-ff5494a92c6a",
        "name": "Dobble: Praia (não é à prova d'água)",
        "id_bgg": 9999538156,
        "price_category": "Faísca",
        "price_base": 20,
        "mechanics": [
            "Reconhecimento de Padrões",
            "Tempo Real"
        ],
        "min_players": 2,
        "max_players": 8,
        "playtime": 15,
        "complexity": 0,
        "theme": "",
        "min_age": 0,
        "slug": "dobble-waterproof",
        "link_ludopedia": "https://ludopedia.com.br/jogo/dobble-waterproof",
        "categories": [
            "Jogo de Cartas",
            "Jogo Festivo"
        ]
    },
    {
        "id": "53ba993f-b486-4e8a-902b-c4e979264a83",
        "name": "Scotland Yard",
        "id_bgg": 1275,
        "price_category": "Fogo",
        "price_base": 40,
        "mechanics": [],
        "min_players": 0,
        "max_players": 0,
        "playtime": 0,
        "complexity": 0,
        "theme": "",
        "min_age": 0,
        "slug": "-221b-baker-street",
        "link_ludopedia": "https://ludopedia.com.br/jogo/-221b-baker-street",
        "categories": []
    },
    {
        "id": "7fefbdbb-c8a5-4361-ad79-52dd0a1b717a",
        "name": "Wiki",
        "id_bgg": 23953,
        "price_category": "Chama",
        "price_base": 30,
        "mechanics": [
            "Jogo em Equipe"
        ],
        "min_players": 4,
        "max_players": 8,
        "playtime": 60,
        "complexity": 0,
        "theme": "",
        "min_age": 0,
        "slug": "wiki",
        "link_ludopedia": "https://ludopedia.com.br/jogo/wiki",
        "categories": [
            "Jogo Festivo"
        ]
    },
    {
        "id": "5c9a81f4-2062-4d5f-a4e3-7636caf44755",
        "name": "Entre Linhas",
        "id_bgg": 300753,
        "price_category": "Chama",
        "price_base": 30,
        "mechanics": [
            "Cooperativo",
            "Dedução"
        ],
        "min_players": 2,
        "max_players": 6,
        "playtime": 10,
        "complexity": 0,
        "theme": "",
        "min_age": 0,
        "slug": "entre-linhas-cross-clues",
        "link_ludopedia": "https://ludopedia.com.br/jogo/entre-linhas-cross-clues",
        "categories": [
            "Jogo de Cartas",
            "Jogo de Entrada",
            "Jogo Festivo"
        ]
    },
    {
        "id": "16ad279a-4a9e-4516-888d-614993a5d286",
        "name": "Perfil 7",
        "id_bgg": 3377,
        "price_category": "Chama",
        "price_base": 30,
        "mechanics": [
            "Movimento Ponto-a-Ponto",
            "Dedução"
        ],
        "min_players": 2,
        "max_players": 6,
        "playtime": 30,
        "complexity": 0,
        "theme": "",
        "min_age": 0,
        "slug": "20-questions",
        "link_ludopedia": "https://ludopedia.com.br/jogo/20-questions",
        "categories": [
            "Jogo Festivo",
            "Trivia"
        ]
    },
    {
        "id": "a6bd65e1-1a05-42c0-a979-1cdf75fd2426",
        "name": "Dobro",
        "id_bgg": 357991,
        "price_category": "Faísca",
        "price_base": 20,
        "mechanics": [
            "Gerenciamento de Mãos",
            "Escalada",
            "Toma Essa"
        ],
        "min_players": 2,
        "max_players": 6,
        "playtime": 15,
        "complexity": 0,
        "theme": "Genérico/Universal",
        "min_age": 0,
        "slug": "dobro",
        "link_ludopedia": "https://ludopedia.com.br/jogo/dobro",
        "categories": [
            "Jogo de Cartas",
            "Jogo de Entrada",
            "Jogo Festivo",
            "Carteado"
        ]
    },
    {
        "id": "3746ab77-f006-47b7-867e-cb2a50874383",
        "name": "Coffee Rush",
        "id_bgg": 377061,
        "price_category": "Fogo",
        "price_base": 40,
        "mechanics": [
            "Contratos",
            "Movimento em Grades"
        ],
        "min_players": 2,
        "max_players": 4,
        "playtime": 30,
        "complexity": 0,
        "theme": "Gastronomia",
        "min_age": 0,
        "slug": "coffee-rush",
        "link_ludopedia": "https://ludopedia.com.br/jogo/coffee-rush",
        "categories": []
    },
    {
        "id": "debbc1b7-c68f-430d-b9e2-202a218831da",
        "name": "Super Lince App",
        "id_bgg": 23953,
        "price_category": "Faísca",
        "price_base": 20,
        "mechanics": [],
        "min_players": 0,
        "max_players": 0,
        "playtime": 0,
        "complexity": 0,
        "theme": "",
        "min_age": 0,
        "slug": "-finders-keepers",
        "link_ludopedia": "https://ludopedia.com.br/jogo/-finders-keepers",
        "categories": []
    },
    {
        "id": "6b4cad05-309b-4d90-b059-d70510d713fd",
        "name": "Geomundo",
        "id_bgg": 418323,
        "price_category": "Faísca",
        "price_base": 20,
        "mechanics": [
            "Memória"
        ],
        "min_players": 2,
        "max_players": 4,
        "playtime": 60,
        "complexity": 0,
        "theme": "",
        "min_age": 0,
        "slug": "geomundo",
        "link_ludopedia": "https://ludopedia.com.br/jogo/geomundo",
        "categories": [
            "Trivia"
        ]
    },
    {
        "id": "7721674c-bd12-4563-8de9-909396b650d9",
        "name": "Harry Potter Escola de Magia",
        "id_bgg": 23953,
        "price_category": "Faísca",
        "price_base": 20,
        "mechanics": [
            "Gerenciamento de Mãos",
            "Movimento Ponto-a-Ponto"
        ],
        "min_players": 2,
        "max_players": 4,
        "playtime": 30,
        "complexity": 0,
        "theme": "Cultura Pop ou Geek",
        "min_age": 0,
        "slug": "harry-potter-escola-de-magia",
        "link_ludopedia": "https://ludopedia.com.br/jogo/harry-potter-escola-de-magia",
        "categories": []
    },
    {
        "id": "2db88328-4016-4573-9fe9-1d4c15f74363",
        "name": "Speed Cups⁶ (6)",
        "id_bgg": 257967,
        "price_category": "Chama",
        "price_base": 30,
        "mechanics": [
            "Reconhecimento de Padrões"
        ],
        "min_players": 2,
        "max_players": 6,
        "playtime": 15,
        "complexity": 0,
        "theme": "",
        "min_age": 0,
        "slug": "speed-cups-6",
        "link_ludopedia": "https://ludopedia.com.br/jogo/speed-cups-6",
        "categories": [
            "Destreza"
        ]
    },
    {
        "id": "3bde5d11-01dd-4cf8-85e7-9bec5ddaec10",
        "name": "Dixit",
        "id_bgg": 39856,
        "price_category": "Fogo",
        "price_base": 40,
        "mechanics": [
            "Narração de Histórias",
            "Votação",
            "Pistas Direcionadas",
            "Corrida"
        ],
        "min_players": 3,
        "max_players": 6,
        "playtime": 30,
        "complexity": 1,
        "theme": "Arte",
        "min_age": 0,
        "slug": "dixit",
        "link_ludopedia": "https://ludopedia.com.br/jogo/dixit",
        "categories": [
            "Jogo de Cartas",
            "Jogo Festivo"
        ]
    },
    {
        "id": "da631d06-9572-4e0e-9a66-740b2e840bd2",
        "name": "The Resistance",
        "id_bgg": 41114,
        "price_category": "Chama",
        "price_base": 30,
        "mechanics": [
            "Seleção de Ação Simultânea",
            "Jogo em Equipe",
            "Votação",
            "Jogadores com Diferentes Habilidades",
            "Apostas e Blefes",
            "Dedução",
            "Posicionamento Secreto"
        ],
        "min_players": 5,
        "max_players": 10,
        "playtime": 30,
        "complexity": 0,
        "theme": "Ficção Científica",
        "min_age": 0,
        "slug": "the-resistance",
        "link_ludopedia": "https://ludopedia.com.br/jogo/the-resistance",
        "categories": [
            "Jogo de Cartas",
            "Jogo Festivo"
        ]
    },
    {
        "id": "b84db761-ce25-4374-aaad-35241dd6b368",
        "name": "Palpite Certo",
        "id_bgg": 123239,
        "price_category": "Chama",
        "price_base": 30,
        "mechanics": [
            "Perguntas e Respostas"
        ],
        "min_players": 3,
        "max_players": 6,
        "playtime": 10,
        "complexity": 0,
        "theme": "",
        "min_age": 0,
        "slug": "palpite-certo",
        "link_ludopedia": "https://ludopedia.com.br/jogo/palpite-certo",
        "categories": [
            "Trivia"
        ]
    },
    {
        "id": "ff1020bc-347b-4b7d-9134-cca5e091c3b6",
        "name": "Time's Up! Party",
        "id_bgg": 230262,
        "price_category": "Chama",
        "price_base": 30,
        "mechanics": [
            "Jogo em Equipe",
            "Memória"
        ],
        "min_players": 4,
        "max_players": 12,
        "playtime": 45,
        "complexity": 0,
        "theme": "",
        "min_age": 0,
        "slug": "time-s-up-party",
        "link_ludopedia": "https://ludopedia.com.br/jogo/time-s-up-party",
        "categories": [
            "Estratégia Abstrata",
            "Jogo Festivo"
        ]
    },
    {
        "id": "9d33664f-fdd6-4e37-8d87-bd3a49f56c14",
        "name": "Botanicus",
        "id_bgg": 413260,
        "price_category": "Vulcão",
        "price_base": 50,
        "mechanics": [
            "Cobertura de Grade",
            "Colecionar Conjuntos",
            "Colocação de Peças",
            "Movimento em Grades",
            "Ordem de Turno: Baseado em Estatísticas",
            "Preparação Variável",
            "Recurso para Mover",
            "Seleção de Ação",
            "Tabuleiro Modular"
        ],
        "min_players": 2,
        "max_players": 4,
        "playtime": 60,
        "complexity": 0,
        "theme": "Economia / Produção",
        "min_age": 0,
        "slug": "botanicus",
        "link_ludopedia": "https://ludopedia.com.br/jogo/botanicus",
        "categories": []
    },
    {
        "id": "8fb3af07-a423-411d-b3c3-8dd5748e366a",
        "name": "Cabanga!",
        "id_bgg": 394889,
        "price_category": "Faísca",
        "price_base": 20,
        "mechanics": [
            "Gerenciamento de Mãos",
            "Combinação"
        ],
        "min_players": 3,
        "max_players": 6,
        "playtime": 20,
        "complexity": 0,
        "theme": "",
        "min_age": 0,
        "slug": "cabanga",
        "link_ludopedia": "https://ludopedia.com.br/jogo/cabanga",
        "categories": [
            "Jogo de Cartas",
            "Jogo de Entrada",
            "Jogo Festivo",
            "Carteado"
        ]
    },
    {
        "id": "1074fb6d-ef5a-4317-8ebd-9beb2a247ae3",
        "name": "Dingo!",
        "id_bgg": 370136,
        "price_category": "Chama",
        "price_base": 30,
        "mechanics": [
            "Colecionar Conjuntos",
            "Movimento em Grades",
            "Habilidades 1 vez por Partida",
            "Movimento com Diferentes Dados",
            "Bingo",
            "Rolar / Girar e Mover",
            "Ordem do Turno: Progressivo"
        ],
        "min_players": 2,
        "max_players": 4,
        "playtime": 20,
        "complexity": 0,
        "theme": "",
        "min_age": 0,
        "slug": "drebo",
        "link_ludopedia": "https://ludopedia.com.br/jogo/drebo",
        "categories": [
            "Estratégia Abstrata",
            "Jogo de Dados"
        ]
    },
    {
        "id": "5632f847-894f-4563-8c60-b595005fe49e",
        "name": "Não Pode",
        "id_bgg": 449031,
        "price_category": "Chama",
        "price_base": 30,
        "mechanics": [
            "Comunicação Limitada",
            "Dedução",
            "Jogo em Equipe",
            "Pistas Direcionadas"
        ],
        "min_players": 4,
        "max_players": 8,
        "playtime": 30,
        "complexity": 0,
        "theme": "Genérico/Universal",
        "min_age": 0,
        "slug": "nao-pode",
        "link_ludopedia": "https://ludopedia.com.br/jogo/nao-pode",
        "categories": [
            "Jogo de Entrada",
            "Jogo Festivo"
        ]
    },
    {
        "id": "f49b12e9-ea38-4e43-ac43-d2d5d09809ea",
        "name": "Galo da Madrugada",
        "id_bgg": 392805,
        "price_category": "Brisa",
        "price_base": 10,
        "mechanics": [
            "Mancala"
        ],
        "min_players": 2,
        "max_players": 4,
        "playtime": 10,
        "complexity": 0,
        "theme": "",
        "min_age": 0,
        "slug": "galo-da-madrugada",
        "link_ludopedia": "https://ludopedia.com.br/jogo/galo-da-madrugada",
        "categories": []
    },
    {
        "id": "89a7b488-6baa-4d3e-baab-399272f7175e",
        "name": "Hokusai",
        "id_bgg": 296027,
        "price_category": "Vulcão",
        "price_base": 50,
        "mechanics": [
            "Colecionar Conjuntos",
            "Construção de Baralho, Bolsas e Peças",
            "Jogadores com Diferentes Habilidades",
            "Reconhecimento de Padrões"
        ],
        "min_players": 2,
        "max_players": 5,
        "playtime": 60,
        "complexity": 0,
        "theme": "Arte",
        "min_age": 0,
        "slug": "hokusai",
        "link_ludopedia": "https://ludopedia.com.br/jogo/hokusai",
        "categories": []
    },
    {
        "id": "d560daaa-e23a-4d85-b311-7748b76c2018",
        "name": "ito",
        "id_bgg": 327778,
        "price_category": "Chama",
        "price_base": 30,
        "mechanics": [
            "Cooperativo",
            "Comunicação Limitada",
            "Dedução",
            "Ordenação"
        ],
        "min_players": 2,
        "max_players": 8,
        "playtime": 10,
        "complexity": 0,
        "theme": "Genérico/Universal",
        "min_age": 0,
        "slug": "ito",
        "link_ludopedia": "https://ludopedia.com.br/jogo/ito",
        "categories": [
            "Jogo de Cartas",
            "Jogo Festivo"
        ]
    },
    {
        "id": "5e5ed663-a048-47b6-86fa-c510ec64cded",
        "name": "Mille Fiori",
        "id_bgg": 346501,
        "price_category": "Fogo",
        "price_base": 40,
        "mechanics": [
            "Influência / Maioria na Área",
            "Compra Fechada",
            "Construção a partir de Modelo"
        ],
        "min_players": 2,
        "max_players": 4,
        "playtime": 90,
        "complexity": 0,
        "theme": "Arte",
        "min_age": 0,
        "slug": "mille-fiori",
        "link_ludopedia": "https://ludopedia.com.br/jogo/mille-fiori",
        "categories": [
            "Jogo de Cartas"
        ]
    },
    {
        "id": "84a4d3b8-00dc-4acf-903f-3ffd7d4ceaa8",
        "name": "Os Desejos do Sultão",
        "id_bgg": 317093,
        "price_category": "Fogo",
        "price_base": 40,
        "mechanics": [
            "Colecionar Conjuntos",
            "Gerenciamento de Mãos",
            "Memória",
            "Alocação de Trabalhadores",
            "Apostas em Metas"
        ],
        "min_players": 1,
        "max_players": 4,
        "playtime": 60,
        "complexity": 0,
        "theme": "Fantasia",
        "min_age": 0,
        "slug": "os-desejos-do-sultao",
        "link_ludopedia": "https://ludopedia.com.br/jogo/os-desejos-do-sultao",
        "categories": []
    },
    {
        "id": "b8385bdf-5fd0-4f55-a9bd-3b2e9d2d6c2d",
        "name": "Sagrada",
        "id_bgg": 199561,
        "price_category": "Fogo",
        "price_base": 40,
        "mechanics": [
            "Colecionar Conjuntos",
            "Construção a partir de Modelo",
            "Rolagem de Dados"
        ],
        "min_players": 1,
        "max_players": 4,
        "playtime": 40,
        "complexity": 0,
        "theme": "Arte",
        "min_age": 0,
        "slug": "sagrada",
        "link_ludopedia": "https://ludopedia.com.br/jogo/sagrada",
        "categories": [
            "Estratégia Abstrata",
            "Jogo de Dados",
            "Quebra-Cabeça"
        ]
    },
    {
        "id": "b2692e34-359c-4c18-86e4-dba0a46d0e66",
        "name": "Sky Team",
        "id_bgg": 373106,
        "price_category": "Fogo",
        "price_base": 40,
        "mechanics": [
            "Comunicação Limitada",
            "Cooperativo",
            "Rolagem de Dados",
            "Alocação de Trabalhadores com Dados",
            "Cenário / Missão / Campanha"
        ],
        "min_players": 0,
        "max_players": 0,
        "playtime": 15,
        "complexity": 0,
        "theme": "Transportes",
        "min_age": 0,
        "slug": "sky-team",
        "link_ludopedia": "https://ludopedia.com.br/jogo/sky-team",
        "categories": [
            "Jogo de Dados"
        ]
    },
    {
        "id": "45f7b2b3-69b5-4860-a5b3-2ae64ff2cce2",
        "name": "Tapple",
        "id_bgg": 129556,
        "price_category": "Fogo",
        "price_base": 40,
        "mechanics": [
            "Perguntas e Respostas"
        ],
        "min_players": 2,
        "max_players": 8,
        "playtime": 20,
        "complexity": 0,
        "theme": "Educacional",
        "min_age": 0,
        "slug": "tapple",
        "link_ludopedia": "https://ludopedia.com.br/jogo/tapple",
        "categories": [
            "Jogo Festivo",
            "Trivia"
        ]
    },
    {
        "id": "f2205ac4-1933-4fd4-b856-6ff948559ae1",
        "name": "Tzolk'in: O Calendário Maia",
        "id_bgg": 126163,
        "price_category": "Vulcão",
        "price_base": 50,
        "mechanics": [
            "Colecionar Conjuntos",
            "Alocação de Trabalhadores",
            "Movimento Direcionado",
            "Bônus de Fim de Jogo",
            "Ordem do Turno: Ação de Reivindicação"
        ],
        "min_players": 2,
        "max_players": 4,
        "playtime": 90,
        "complexity": 3.67,
        "theme": "História",
        "min_age": 0,
        "slug": "tzolk-in-the-mayan-calendar",
        "link_ludopedia": "https://ludopedia.com.br/jogo/tzolk-in-the-mayan-calendar",
        "categories": []
    },
    {
        "id": "6b174762-22ab-42dc-aa54-b193ba48521d",
        "name": "Village Green",
        "id_bgg": 300583,
        "price_category": "Chama",
        "price_base": 30,
        "mechanics": [
            "Gerenciamento de Mãos",
            "Colecionar Conjuntos",
            "Construção a partir de Modelo"
        ],
        "min_players": 1,
        "max_players": 5,
        "playtime": 30,
        "complexity": 0,
        "theme": "Arte",
        "min_age": 0,
        "slug": "village-green",
        "link_ludopedia": "https://ludopedia.com.br/jogo/village-green",
        "categories": [
            "Jogo de Cartas"
        ]
    },
    {
        "id": "9e159659-43d5-4535-bb5c-cb4ecfd0427d",
        "name": "Os Desejos do Sultão: Jogo base + Expansão Viajantes",
        "id_bgg": 392704,
        "price_category": "Vulcão",
        "price_base": 50,
        "mechanics": [
            "Colecionar Conjuntos",
            "Gerenciamento de Mãos",
            "Memória",
            "Alocação de Trabalhadores",
            "Apostas em Metas"
        ],
        "min_players": 2,
        "max_players": 4,
        "playtime": 90,
        "complexity": 0,
        "theme": "Animais",
        "min_age": 14,
        "slug": "os-desejos-do-sultao-expansao-viajantes",
        "link_ludopedia": "https://ludopedia.com.br/jogo/os-desejos-do-sultao-expansao-viajantes",
        "categories": [
            "Jogo Assimétrico"
        ]
    },
    {
        "id": "ec97794a-3521-482f-9a95-5a926e502bef",
        "name": "Brazil Imperial",
        "id_bgg": 249277,
        "price_category": "Vulcão",
        "price_base": 50,
        "mechanics": [
            "Colecionar Conjuntos",
            "Tabuleiro Modular",
            "Influência / Maioria na Área",
            "Gerenciamento de Mãos",
            "Jogadores com Diferentes Habilidades",
            "Movimento em Grades"
        ],
        "min_players": 1,
        "max_players": 4,
        "playtime": 100,
        "complexity": 0,
        "theme": "Cultura Brasileira",
        "min_age": 14,
        "slug": "brazil-imperial",
        "link_ludopedia": "https://ludopedia.com.br/jogo/brazil-imperial",
        "categories": [
            "4x"
        ]
    },
    {
        "id": "791cc47c-3f78-451b-8222-8a5159d4e7f6",
        "name": "Ticket to Ride",
        "id_bgg": 9209,
        "price_category": "Fogo",
        "price_base": 40,
        "mechanics": [
            "Gerenciamento de Mãos",
            "Construção de Redes e Rotas",
            "Bônus de Fim de Jogo",
            "Colecionar Conjuntos",
            "Compra Aberta",
            "Conexões",
            "Contratos",
            "Force sua sorte"
        ],
        "min_players": 2,
        "max_players": 5,
        "playtime": 45,
        "complexity": 0,
        "theme": "Transportes",
        "min_age": 8,
        "slug": "ticket-to-ride",
        "link_ludopedia": "https://ludopedia.com.br/jogo/ticket-to-ride",
        "categories": [
            "Jogo de Entrada"
        ]
    },
    {
        "id": "9d336654-a6ab-44ca-9bfb-960b4911d3d3",
        "name": "Quorum",
        "id_bgg": 429851,
        "price_category": "Chama",
        "price_base": 30,
        "mechanics": [
            "Bônus de Fim de Jogo",
            "Colecionar Conjuntos",
            "Gerenciamento de Mãos"
        ],
        "min_players": 2,
        "max_players": 4,
        "playtime": 60,
        "complexity": 0,
        "theme": "História",
        "min_age": 14,
        "slug": "quorum",
        "link_ludopedia": "https://ludopedia.com.br/jogo/quorum",
        "categories": []
    },
    {
        "id": "383252fa-eea6-4909-90e0-e221ed10ba2b",
        "name": "Bingo",
        "id_bgg": 7316,
        "price_category": "Fogo",
        "price_base": 40,
        "mechanics": [
            "Reconhecimento de Padrões",
            "Bingo",
            "Apostas e Blefes"
        ],
        "min_players": 2,
        "max_players": 2,
        "playtime": 60,
        "complexity": 0,
        "theme": "Cultura Pop ou Geek",
        "min_age": 5,
        "slug": "bingo",
        "link_ludopedia": "https://ludopedia.com.br/jogo/bingo",
        "categories": [
            "Jogo Festivo"
        ]
    },
    {
        "id": "7862684a-1964-4bfe-a4c0-8cf494e0bbe6",
        "name": "Honey Buzz",
        "id_bgg": 284742,
        "price_category": "Vulcão",
        "price_base": 50,
        "mechanics": [
            "Alocação de Trabalhadores",
            "Colocação de Peças",
            "Construção a partir de Modelo",
            "Recuperação de Ação",
            "Contratos",
            "Movimento em Grades",
            "Grade Hexagonal",
            "Compra Aberta",
            "Solo / Solitário",
            "Grade com Quadrados"
        ],
        "min_players": 1,
        "max_players": 4,
        "playtime": 90,
        "complexity": 0,
        "theme": "Animais",
        "min_age": 10,
        "slug": "honey-buzz",
        "link_ludopedia": "https://ludopedia.com.br/jogo/honey-buzz",
        "categories": []
    },
    {
        "id": "07999d31-5340-475c-9641-94ec8badcd1a",
        "name": "Verdade ou Desafio?",
        "id_bgg": 14707,
        "price_category": "Chama",
        "price_base": 30,
        "mechanics": [
            "Perguntas e Respostas",
            "Rolar / Girar e Mover"
        ],
        "min_players": 2,
        "max_players": 4,
        "playtime": 20,
        "complexity": 0,
        "theme": "",
        "min_age": 7,
        "slug": "verdade-ou-desafio",
        "link_ludopedia": "https://ludopedia.com.br/jogo/verdade-ou-desafio",
        "categories": [
            "Jogo Festivo"
        ]
    }
]